{
  "fontFamilies": {
    "inter": {
      "$type": "fontFamilies",
      "$value": "Inter"
    }
  },
  "fontWeights": {
    "inter-bold": {
      "$type": "fontWeights",
      "$value": "Bold"
    },
    "inter-semibold": {
      "$type": "fontWeights",
      "$value": "Semibold"
    },
    "inter-medium": {
      "$type": "fontWeights",
      "$value": "Medium"
    },
    "inter-regular": {
      "$type": "fontWeights",
      "$value": "Regular"
    },
    "inter-light": {
      "$type": "fontWeights",
      "$value": "Light"
    }
  }
}