{
  "button": {
    "default": {
      "$type": "composition",
      "$value": {
        "typography": "{typography.body.emphasized}",
        "borderRadius": "{radii.xs}",
        "horizontalPadding": "{spacing.7}",
        "verticalPadding": "{spacing.2}",
        "itemSpacing": "{spacing.3}",
        "height": "{height.5}"
      }
    },
    "default-icon": {
      "$type": "composition",
      "$value": {
        "typography": "{typography.body.emphasized}",
        "borderRadius": "{radii.xs}",
        "sizing": "{height.5}"
      }
    }
  }
}